mars_uartCmd/__init__.py
mars_uartCmd/cmd.py
mars_uartCmd-0.0.4.dist-info/METADATA
mars_uartCmd-0.0.4.dist-info/WHEEL
mars_uartCmd-0.0.4.dist-info/top_level.txt
mars_uartCmd-0.0.4.dist-info/RECORD
