Metadata-Version: 2.1
Name: mars-uartCmd
Version: 0.0.4
Requires-Dist: numpy
Requires-Dist: pyserial
Requires-Dist: tqdm
